pdfimposeweb/__init__.py
pdfimposeweb/database.py
pdfimposeweb/limiter.py
pdfimposeweb/layout/__init__.py
pdfimposeweb/layout/cards.py
pdfimposeweb/layout/common.py
pdfimposeweb/layout/copycutfold.py
pdfimposeweb/layout/cutstackfold.py
pdfimposeweb/layout/hardcover.py
pdfimposeweb/layout/onepagezine.py
pdfimposeweb/layout/pdfautonup.py
pdfimposeweb/layout/saddle.py
pdfimposeweb/layout/wire.py
pdfimposeweb/pdfresize/__init__.py
pdfimposeweb/pdfresize/__main__.py
pdfimposeweb/settings/__init__.py
pdfimposeweb/settings/default.py
pdfimposeweb/static/Makefile
pdfimposeweb/static/android-chrome-192x192.png
pdfimposeweb/static/android-chrome-512x512.png
pdfimposeweb/static/apple-touch-icon.png
pdfimposeweb/static/browserconfig.xml
pdfimposeweb/static/favicon-16x16.png
pdfimposeweb/static/favicon-32x32.png
pdfimposeweb/static/favicon.ico
pdfimposeweb/static/logo.aux
pdfimposeweb/static/logo.log
pdfimposeweb/static/logo.png
pdfimposeweb/static/logo.tex
pdfimposeweb/static/mastodon.svg
pdfimposeweb/static/mstile-150x150.png
pdfimposeweb/static/safari-pinned-tab.svg
pdfimposeweb/static/site.webmanifest
pdfimposeweb/static/style.css
pdfimposeweb/static/upload.js
pdfimposeweb/static/bootstrap/README.txt
pdfimposeweb/static/bootstrap/bootstrap.bundle.min.js
pdfimposeweb/static/bootstrap/bootstrap.min.css
pdfimposeweb/static/bootstrap/mastodon.svg
pdfimposeweb/static/bootstrap/translate.svg
pdfimposeweb/static/layout/library.svg
pdfimposeweb/static/layout/cards/cards-horizontal.svg
pdfimposeweb/static/layout/cards/cards-vertical.svg
pdfimposeweb/static/layout/copycutfold/copycutfold-horizontal.svg
pdfimposeweb/static/layout/copycutfold/copycutfold-vertical.svg
pdfimposeweb/static/layout/cutstackfold/cutstackfold-horizontal.svg
pdfimposeweb/static/layout/cutstackfold/cutstackfold-vertical.svg
pdfimposeweb/static/layout/hardcover/hardcover-horizontal.svg
pdfimposeweb/static/layout/hardcover/hardcover-vertical.svg
pdfimposeweb/static/layout/onepagezine/onepagezine-horizontal.svg
pdfimpose_web-1.4.1.dist-info/METADATA
pdfimpose_web-1.4.1.dist-info/WHEEL
pdfimpose_web-1.4.1.dist-info/entry_points.txt
pdfimpose_web-1.4.1.dist-info/licenses/AUTHORS
pdfimpose_web-1.4.1.dist-info/licenses/LICENSE
pdfimpose_web-1.4.1.dist-info/RECORD
