Metadata-Version: 2.4
Name: pdfimpose-web
Version: 1.4.1
Summary: The code powering https://pdfimpose.it
Project-URL: Homepage, https://pdfimpose.it
Project-URL: Issues, https://framagit.org/spalax/pdfimpose-web/issues
Author-email: Louis Paternault <spalax@gresille.org>
License-File: AUTHORS
License-File: LICENSE
Keywords: imposition,pdf,print,web
Classifier: Development Status :: 5 - Production/Stable
Classifier: Framework :: Flask
Classifier: License :: OSI Approved :: GNU Affero General Public License v3 or later (AGPLv3+)
Classifier: Programming Language :: Python :: 3.10
Classifier: Programming Language :: Python :: 3.11
Classifier: Programming Language :: Python :: 3.12
Classifier: Programming Language :: Python :: 3.13
Classifier: Programming Language :: Python :: 3.14
Classifier: Topic :: Printing
Requires-Python: >=3.10
Requires-Dist: flask-babel>=4
Requires-Dist: flask-basicauth
Requires-Dist: flask-limiter
Requires-Dist: flask-sqlalchemy
Requires-Dist: flask>=3
Requires-Dist: papersize>=1.5
Requires-Dist: pdfautonup>=1.12.1
Requires-Dist: pdfimpose>=2.8.0
Requires-Dist: pymupdf>=1.24.3
Requires-Dist: unidecode
